ircevents/__init__.py
ircevents/engine.py
ircevents/helpers.py
ircevents-0.3.0.dist-info/LICENSE
ircevents-0.3.0.dist-info/METADATA
ircevents-0.3.0.dist-info/WHEEL
ircevents-0.3.0.dist-info/top_level.txt
ircevents-0.3.0.dist-info/RECORD
