Metadata-Version: 2.1
Name: ircevents
Version: 0.3.0
Summary: UNKNOWN
Home-page: https://github.com/aewens/ircevents
Author: aewens
Author-email: email@aewens.com
License: UNKNOWN
Platform: UNKNOWN
Classifier: Programming Language :: Python :: 3
Classifier: License :: OSI Approved :: BSD License
Classifier: Operating System :: OS Independent
Classifier: Topic :: Communications :: Chat :: Internet Relay Chat
Requires-Python: >=3.6
